txt2epub/__init__.py
txt2epub/__main__.py
txt2epub/txt2epub.py
txt2epub/txt2epub_gui.py
txt2epub/utils.py
txt2epub-1.4.0.dist-info/METADATA
txt2epub-1.4.0.dist-info/WHEEL
txt2epub-1.4.0.dist-info/entry_points.txt
txt2epub-1.4.0.dist-info/licenses/LICENSE
txt2epub-1.4.0.dist-info/RECORD
