Metadata-Version: 2.4
Name: txt2epub
Version: 1.4.0
Summary: A simple TXT to EPUB converter
Project-URL: homepage, https://github.com/k4yt3x/txt2epub/
Author-email: K4YT3X <i@k4yt3x.com>
License: GPL-2.0-only
License-File: LICENSE
Keywords: ebook
Classifier: Environment :: Console
Classifier: Environment :: X11 Applications :: Qt
Classifier: Operating System :: OS Independent
Classifier: Programming Language :: Python
Classifier: Programming Language :: Python :: 3
Requires-Python: >=3.8
Requires-Dist: ebooklib>=0.18
Requires-Dist: langdetect>=1.0.0
Requires-Dist: pillow>=10.4.0
Requires-Dist: pyqt6>=6.5.0
